{"add":{"path":"Company_Name=JKTYRE/part-00000-79cf1000-95bc-4b03-b18c-e306372eae21.c000.snappy.parquet","partitionValues":{"Company_Name":"JKTYRE"},"size":10535,"modificationTime":1649310720583,"dataChange":true}}
{"commitInfo":{"timestamp":1649310720587,"operation":"WRITE","operationParameters":{"mode":"Append","partitionBy":"[\"Company_Name\"]"},"readVersion":268,"isolationLevel":"Serializable","isBlindAppend":true,"operationMetrics":{"numFiles":"1","numOutputRows":"248","numOutputBytes":"10535"},"engineInfo":"Apache-Spark/3.2.1 Delta-Lake/1.1.0"}}
