{"add":{"path":"Company_Name=HINDZINC/part-00000-316f49c9-b94c-4f61-8408-db6d95e5bb3e.c000.snappy.parquet","partitionValues":{"Company_Name":"HINDZINC"},"size":10480,"modificationTime":1649310715295,"dataChange":true}}
{"commitInfo":{"timestamp":1649310715303,"operation":"WRITE","operationParameters":{"mode":"Append","partitionBy":"[\"Company_Name\"]"},"readVersion":263,"isolationLevel":"Serializable","isBlindAppend":true,"operationMetrics":{"numFiles":"1","numOutputRows":"248","numOutputBytes":"10480"},"engineInfo":"Apache-Spark/3.2.1 Delta-Lake/1.1.0"}}
