{"add":{"path":"Company_Name=PHOENIXLTD/part-00000-8400008a-1339-4cb0-82fb-abe4589fbb68.c000.snappy.parquet","partitionValues":{"Company_Name":"PHOENIXLTD"},"size":10103,"modificationTime":1649311642685,"dataChange":true}}
{"commitInfo":{"timestamp":1649311642693,"operation":"WRITE","operationParameters":{"mode":"Append","partitionBy":"[\"Company_Name\"]"},"readVersion":912,"isolationLevel":"Serializable","isBlindAppend":true,"operationMetrics":{"numFiles":"1","numOutputRows":"248","numOutputBytes":"10103"},"engineInfo":"Apache-Spark/3.2.1 Delta-Lake/1.1.0"}}
